agilicus/.gitignore
agilicus/.openapi-generator/FILES
agilicus/.openapi-generator/VERSION
agilicus/.openapi-generator-ignore
agilicus/__init__.py
agilicus/access.py
agilicus/agilicus_api/__init__.py
agilicus/agilicus_api/api/__init__.py
agilicus/agilicus_api/api/application_services_api.py
agilicus/agilicus_api/api/application_services_api_mock.py
agilicus/agilicus_api/api/applications_api.py
agilicus/agilicus_api/api/applications_api_mock.py
agilicus/agilicus_api/api/audits_api.py
agilicus/agilicus_api/api/audits_api_mock.py
agilicus/agilicus_api/api/billing_api.py
agilicus/agilicus_api/api/billing_api_mock.py
agilicus/agilicus_api/api/catalogues_api.py
agilicus/agilicus_api/api/catalogues_api_mock.py
agilicus/agilicus_api/api/certificates_api.py
agilicus/agilicus_api/api/certificates_api_mock.py
agilicus/agilicus_api/api/challenges_api.py
agilicus/agilicus_api/api/challenges_api_mock.py
agilicus/agilicus_api/api/connectors_api.py
agilicus/agilicus_api/api/connectors_api_mock.py
agilicus/agilicus_api/api/diagnostics_api.py
agilicus/agilicus_api/api/diagnostics_api_mock.py
agilicus/agilicus_api/api/features_api.py
agilicus/agilicus_api/api/features_api_mock.py
agilicus/agilicus_api/api/files_api.py
agilicus/agilicus_api/api/files_api_mock.py
agilicus/agilicus_api/api/groups_api.py
agilicus/agilicus_api/api/groups_api_mock.py
agilicus/agilicus_api/api/issuers_api.py
agilicus/agilicus_api/api/issuers_api_mock.py
agilicus/agilicus_api/api/launchers_api.py
agilicus/agilicus_api/api/launchers_api_mock.py
agilicus/agilicus_api/api/lookups_api.py
agilicus/agilicus_api/api/lookups_api_mock.py
agilicus/agilicus_api/api/messages_api.py
agilicus/agilicus_api/api/messages_api_mock.py
agilicus/agilicus_api/api/metrics_api.py
agilicus/agilicus_api/api/metrics_api_mock.py
agilicus/agilicus_api/api/organisations_api.py
agilicus/agilicus_api/api/organisations_api_mock.py
agilicus/agilicus_api/api/permissions_api.py
agilicus/agilicus_api/api/permissions_api_mock.py
agilicus-1.157.1.dist-info/entry_points.txt
agilicus-1.157.1.dist-info/LICENSE.txt
agilicus-1.157.1.dist-info/WHEEL
agilicus-1.157.1.dist-info/METADATA
agilicus-1.157.1.dist-info/RECORD
