Metadata-Version: 2.1
Name: agilicus
Version: 1.157.1
Summary: Agilicus SDK
Home-page: https://www.agilicus.com/
License: MIT
Author: Agilicus Devs
Author-email: dev@agilicus.com
Requires-Python: >=3.7,<4.0
Classifier: License :: OSI Approved :: MIT License
Classifier: Programming Language :: Python :: 3
Classifier: Programming Language :: Python :: 3.10
Classifier: Programming Language :: Python :: 3.7
Classifier: Programming Language :: Python :: 3.8
Classifier: Programming Language :: Python :: 3.9
Provides-Extra: billing
Requires-Dist: PyJWT (>=2.4.0,<2.5.0)
Requires-Dist: certifi (>=14.05.14)
Requires-Dist: click (>=8.0.0,<9.0.0)
Requires-Dist: colorama (>=0.4.3,<0.5.0)
Requires-Dist: cryptography (>=3.1.1,<4.0.0)
Requires-Dist: ipapi (==1.0.4)
Requires-Dist: keyring (>=23.0.0)
Requires-Dist: oauth2client (>=4.1.3,<4.2.0)
Requires-Dist: paho-mqtt (>=1.6.1,<2.0.0)
Requires-Dist: prettytable (>=0.7.2,<0.8.0)
Requires-Dist: prometheus_client (==0.11.0); extra == "billing"
Requires-Dist: python_dateutil (>2.5.3)
Requires-Dist: pyyaml (==5.4.1)
Requires-Dist: requests (>=2.23.0,<3.0.0)
Requires-Dist: six (>=1.14.0,<2.0.0)
Requires-Dist: stripe (>=2.60.0,<3.0.0); extra == "billing"
Project-URL: Repository, https://github.com/Agilicus
